<?xml version="1.0" encoding="utf-8"?>
<Defs>
  <!--
  <GatheringDef>
    <defName>DIL_Gathering_Storytelling</defName>
    <label>storytelling</label>
    <randomSelectionWeight>0</randomSelectionWeight>
    <letterTitle>Storytelling</letterTitle>
    <letterText>{ORGANIZER_labelShort} is telling a story.</letterText>
    <calledOffMessage>The story was interrupted.</calledOffMessage>
    <finishedMessage>The storytelling is finished.</finishedMessage>
    <duty>DIL_Duty_Storytelling_Organizer</duty>
    <workerClass>DIL_PositiveConnections.GatheringWorker_Storytelling</workerClass>
    <gatherSpotDefs>
      <li>PartySpot</li>
    </gatherSpotDefs>
  </GatheringDef>
-->
</Defs>